ipapython/__init__.py
ipapython/admintool.py
ipapython/certdb.py
ipapython/config.py
ipapython/cookie.py
ipapython/directivesetter.py
ipapython/dn.py
ipapython/dn_ctypes.py
ipapython/dnsutil.py
ipapython/dogtag.py
ipapython/errors.py
ipapython/fqdn.py
ipapython/graph.py
ipapython/ipa_log_manager.py
ipapython/ipachangeconf.py
ipapython/ipaldap.py
ipapython/ipautil.py
ipapython/ipavalidate.py
ipapython/kerberos.py
ipapython/kernel_keyring.py
ipapython/nsslib.py
ipapython/session_storage.py
ipapython/ssh.py
ipapython/version.py
ipapython-4.12.2.dist-info/COPYING
ipapython-4.12.2.dist-info/METADATA
ipapython-4.12.2.dist-info/WHEEL
ipapython-4.12.2.dist-info/top_level.txt
ipapython-4.12.2.dist-info/RECORD
